calc_ev_115/__init__.py
calc_ev_115/__main__.py
calc_ev_115/calc_ev_115.py
calc_ev_115/test_calculator.py
calc_ev_115-0.0.1.dist-info/LICENSE
calc_ev_115-0.0.1.dist-info/METADATA
calc_ev_115-0.0.1.dist-info/WHEEL
calc_ev_115-0.0.1.dist-info/top_level.txt
calc_ev_115-0.0.1.dist-info/RECORD
