Metadata-Version: 2.1
Name: calc-ev-115
Version: 0.0.1
Summary: simple calculator
Home-page: https://github.com/EVitkunaite
Author: Egle Vitkunaite
Author-email: egle3ph0@gmail.com
License: UNKNOWN
Platform: UNKNOWN
Classifier: Programming Language :: Python :: 3
Classifier: License :: OSI Approved :: MIT License
Classifier: Operating System :: OS Independent
Requires-Python: >=3.7
